{
  "meta_title": "",
  "meta_description": "",
  "sections": [
    {
      "type": "banner-slider",
      "autoplay": 9000,
      "full_width": true,
      "slides": [
        {
          "img": "/img/uploads/cabeceirasd.jpg",
          "link": "",
          "alt": "",
          "start": "2020-04-11T05:54:06.750Z",
          "end": "",
          "mobile_img": "/img/uploads/cabeceirasmobile.jpg"
        },
        {
          "start": "2022-10-17T03:00:00.000Z",
          "end": "",
          "img": "/img/uploads/camabox.jpg",
          "alt": "",
          "mobile_img": "/img/uploads/camaboxm.jpg"
        }
      ]
    },
    {
      "type": "responsive-banner",
      "img": "/img/uploads/faixades.jpg",
      "mobile_img": "/img/uploads/faixamobile.jpg"
    },
    {
      "type": "collection-shelf",
      "shuffle": true,
      "collection_id": null,
      "sort": "news",
      "title": "",
      "headless": false,
      "limit": 12,
      "page": 1
    },
    {
      "type": "info-bar",
      "enabled": true
    }
  ]
}